xfaas_core_python3/xfunction.py
xfaas_core_python3/xrunner.py
xfaas_core_python3/adapter/__init__.py
xfaas_core_python3/adapter/xfaas_entry.py
xfaas_core_python3-0.0.5.dist-info/LICENSE
xfaas_core_python3-0.0.5.dist-info/METADATA
xfaas_core_python3-0.0.5.dist-info/WHEEL
xfaas_core_python3-0.0.5.dist-info/top_level.txt
xfaas_core_python3-0.0.5.dist-info/RECORD
