Metadata-Version: 2.1
Name: xfaas-core-python3
Version: 0.0.5
Summary: XFaaS package for Python3
Author-email: Paul Wieland <paul.wieland@tum.de>
Project-URL: Homepage, https://github.com/Function-Delivery-Network/FaaS-Shim
Project-URL: Function Templates , https://github.com/paul-wie/xfaas-templates
Classifier: Programming Language :: Python :: 3
Classifier: License :: OSI Approved :: MIT License
Classifier: Operating System :: OS Independent
Requires-Python: >=3.7
License-File: LICENSE
